RTL/ADDER.v
/*
    Created             : /home/caonam/SNN_THESIS_PROJECT/RTL/ADDER.v
    Module Name         : ADDER
    Author              : Van Nam CAO
    Date                : 08 - 07 - 2025
    Description         : This module that perform 32-bit floating point addition
*/

`timescale 1ns / 1ps
module ADDER (
    input         [31:0]  A,
    input         [31:0]  B,

    output  reg   [31:0]  SUM
);

    //Extract components of IEEE 754 format
    wire                  SIGN_A  =   A[31];
    wire                  SIGB_B  =   B[31];
    wire          [7:0]   EXP_A   =   A[30:23];
    wire          [7:0]   EXP_B   =   B[30:23];
    wire          [23:0]  MAN_A   =   (A[30:23] == 0) ? {1'b0, A[22:0]} : {1'b1, A[22:0]};
    wire          [23:0]  MAN_B   =   (B[30:23] == 0) ? {1'b0, B[22:0]} : {1'b1, B[22:0]};
    
    wire          [7:0]   EXP_D;
    wire          [23:0]  AL_MA, AL_MB;
    wire          [7:0]   L_EXP;

    wire          [24:0]  MAN_S;
    reg           [24:0]  ABS_A, ABS_B;
    reg                   OP_SI;

    reg           [7:0]   R_EXP;
    reg           [23:0]  R_MAN;
    reg                   R_SIG;

    integer               S_COU;


    // Align exponents
    assign                EXP_D   =   (EXP_A > EXP_B) ? (EXP_A - EXP_B) : (EXP_B - EXP_A);
    assign                L_EXP   =   (EXP_A > EXP_B) ? EXP_A : EXP_B;
    assign                AL_MA   =   (EXP_A > EXP_B) ? MAN_A : (MAN_A >> EXP_D);
    assign                AL_MB   =   (EXP_B > EXP_A) ? MAN_B : (MAN_B >> EXP_D);
    
    // Perform addition or subtraction based on signs
    always@(*) begin
      if(AL_MA >= AL_MB) begin
        ABS_A   =   {1'b0, AL_MA};
        ABS_B   =   {1'b0, AL_MB};
        OP_SI   =   SIGN_A;
      end else begin
        ABS_A   =   {1'b0, AL_MB};
        ABS_B   =   {1'b0, AL_MB};
        OP_SI   =   SIGB_B;
      end
    end
    
    assign                MAN_S   =   (SIGN_A == SIGB_B) ? (AL_MA + AL_MB) : (ABS_A - ABS_B);

    // Normalize the result
    always@(*) begin
      if(MAN_S[24]) begin
        R_MAN   =   MAN_S[24:1];
        R_EXP   =   L_EXP + 1;

      end else begin
        R_MAN   =   MAN_S[23:0];
        R_EXP   =   L_EXP;

        for(S_COU = 0; S_COU < 24; S_COU = S_COU + 1) begin
          if(R_MAN[23] == 1'b0 && R_EXP > 0 ) begin
            R_MAN   =   R_MAN << 1;
            R_EXP   =   R_EXP - 1;
          end
        end
      end
      R_SIG   =   (MAN_S == 0) ? 0 : OP_SI;
    end

    // Handle special cases (zero cases)
    always @(*) begin
      if(A[30:0] == 0)
        SUM   =   B;

      else if (B[30:0] == 0)
        SUM   =   A;

      else
        SUM   =   {R_SIG, R_EXP, R_MAN[22:0]};      
    end

endmodule

TB/ADDER_TB.v
// Testbench for 32-bit Floating-Point Adder

module ADDER_TB;
    // Inputs
    reg [31:0] a;
    reg [31:0] b;

    // Output
    wire [31:0] result;

    // Instantiate the floating_point_adder module
    ADDER uut (
        .A(a),
        .B(b),
        .SUM(result)
    );

    // Task to display results
    task display_result;
        input [31:0] op1, op2, res;
        begin
            $display("A = %h, B = %h, Result = %h", op1, op2, res);
        end
    endtask

    // Test procedure
    initial begin
        // Monitor signals
        $monitor($time, " A = %h, B = %h, Result = %h", a, b, result);

         // Test Case 1: Add two positive numbers
        a = 32'h40400000; // 3.0 in IEEE 754
        b = 32'h40800000; // 4.0 in IEEE 754
        #10;
        display_result(a, b, result);

        // Test Case 2: Add a positive and a negative number
        a = 32'hC0400000; // -3.0 in IEEE 754
        b = 32'h40800000; // 4.0 in IEEE 754
        #10;
        display_result(a, b, result);

        // Test Case 3: Add two negative numbers
        a = 32'hC0400000; // -3.0 in IEEE 754
        b = 32'hC0800000; // -4.0 in IEEE 754
        #10;
        display_result(a, b, result);

        // Test Case 4: Add zero
        a = 32'h00000000; // 0.0 in IEEE 754
        b = 32'h40800000; // 4.0 in IEEE 754
        #10;
        display_result(a, b, result);

        // Test Case 5: Add two very small numbers
        a = 32'h33800000; // 1.0e-40 in IEEE 754
        b = 32'h33800000; // 1.0e-40 in IEEE 754
        #10;
        display_result(a, b, result);

        // Test Case 6: Add infinity
        a = 32'h7F800000; // +Infinity in IEEE 754
        b = 32'h3F800000; // 1.0 in IEEE 754
        #10;
        display_result(a, b, result);

        // Test Case 7: Add NaN
        a = 32'h7FC00000; // NaN in IEEE 754
        b = 32'h3F800000; // 1.0 in IEEE 754
        #10;
        display_result(a, b, result);

        // Additional Test Cases for opposite signs
        // Test Case 8: Subtracting positive from negative
        a = 32'hC1200000; // -10.0 in IEEE 754
        b = 32'h41200000; // 10.0 in IEEE 754
        #10;
        display_result(a, b, result);

        // Test Case 9: Subtracting negative from positive
        a = 32'h41200000; // 10.0 in IEEE 754
        b = 32'hC1200000; // -10.0 in IEEE 754
        #10;
        display_result(a, b, result);

        // Test Case 10: Add small negative to large positive
        a = 32'hC0000000; // -2.0 in IEEE 754
        b = 32'h42000000; // 32.0 in IEEE 754
        #10;
        display_result(a, b, result);

        // Test Case 11: Add large negative to small positive
        a = 32'hC2000000; // -32.0 in IEEE 754
        b = 32'h40000000; // 2.0 in IEEE 754
        #10;
        display_result(a, b, result);

	// Test Case 10: Add small negative to large positive
	a = 32'hC0600000; // -3.5 in IEEE 754
	b = 32'h40A66666; // 5.2 in IEEE 754
	#10;

	// Test Case 10: Add small negative to large positive
	a = 32'h40C00000; // -3.5 in IEEE 754
	b = 32'hC1406000; // 5.2 in IEEE 754
	#10;

        $stop;
    end
  
  	initial begin
    	$dumpfile("../RESULTS/waveform.vcd"); // T n file VCD
    	$dumpvars(0, adder_tb); // ??t m?c ?? ghi t n hi?u
	end
endmodule

RESULTS/waveform.vcd
$version Generated by VerilatedVcd $end
$timescale 1ps $end
 $scope module TOP $end
  $scope module ADDER_TB $end
   $var wire 32 # a [31:0] $end
   $var wire 32 $ b [31:0] $end
   $var wire 32 5 result [31:0] $end
   $scope module uut $end
    $var wire 32 # A [31:0] $end
    $var wire 32 $ B [31:0] $end
    $var wire 32 5 SUM [31:0] $end
    $var wire 1 % SIGN_A $end
    $var wire 1 & SIGB_B $end
    $var wire 8 ' EXP_A [7:0] $end
    $var wire 8 ( EXP_B [7:0] $end
    $var wire 24 ) MAN_A [23:0] $end
    $var wire 24 * MAN_B [23:0] $end
    $var wire 8 + EXP_D [7:0] $end
    $var wire 24 , AL_MA [23:0] $end
    $var wire 24 - AL_MB [23:0] $end
    $var wire 8 . L_EXP [7:0] $end
    $var wire 25 / MAN_S [24:0] $end
    $var wire 25 0 ABS_A [24:0] $end
    $var wire 25 1 ABS_B [24:0] $end
    $var wire 1 6 OP_SI $end
    $var wire 8 2 R_EXP [7:0] $end
    $var wire 24 3 R_MAN [23:0] $end
    $var wire 1 7 R_SIG $end
    $var wire 32 4 S_COU [31:0] $end
   $upscope $end
  $upscope $end
 $upscope $end
$enddefinitions $end


#0
b01000000010000000000000000000000 #
b01000000100000000000000000000000 $
0%
0&
b10000000 '
b10000001 (
b110000000000000000000000 )
b100000000000000000000000 *
b00000001 +
b011000000000000000000000 ,
b100000000000000000000000 -
b10000001 .
b0111000000000000000000000 /
b0100000000000000000000000 0
b0011000000000000000000000 1
b10000001 2
b111000000000000000000000 3
b00000000000000000000000000011000 4
b01000000111000000000000000000000 5
06
07
#10000
b11000000010000000000000000000000 #
1%
b0001000000000000000000000 /
b01111111 2
b100000000000000000000000 3
b00111111100000000000000000000000 5
#20000
b11000000100000000000000000000000 $
1&
b0111000000000000000000000 /
b10000001 2
b111000000000000000000000 3
b11000000111000000000000000000000 5
16
17
#30000
b00000000000000000000000000000000 #
b01000000100000000000000000000000 $
0%
0&
b00000000 '
b000000000000000000000000 )
b10000001 +
b000000000000000000000000 ,
b0100000000000000000000000 /
b0000000000000000000000000 1
b100000000000000000000000 3
b01000000100000000000000000000000 5
06
07
#40000
b00110011100000000000000000000000 #
b00110011100000000000000000000000 $
b01100111 '
b01100111 (
b100000000000000000000000 )
b00000000 +
b100000000000000000000000 ,
b01100111 .
b1000000000000000000000000 /
b0100000000000000000000000 1
b01101000 2
b00110100000000000000000000000000 5
#50000
b01111111100000000000000000000000 #
b00111111100000000000000000000000 $
b11111111 '
b01111111 (
b10000000 +
b000000000000000000000000 -
b11111111 .
b0100000000000000000000000 /
b0000000000000000000000000 1
b11111111 2
b01111111100000000000000000000000 5
#60000
b01111111110000000000000000000000 #
b110000000000000000000000 )
b110000000000000000000000 ,
b0110000000000000000000000 /
b0110000000000000000000000 0
b110000000000000000000000 3
b01111111110000000000000000000000 5
#70000
b11000001001000000000000000000000 #
b01000001001000000000000000000000 $
1%
b10000010 '
b10000010 (
b101000000000000000000000 )
b101000000000000000000000 *
b00000000 +
b101000000000000000000000 ,
b101000000000000000000000 -
b10000010 .
b0000000000000000000000000 /
b0101000000000000000000000 0
b0101000000000000000000000 1
b01101010 2
b000000000000000000000000 3
b00110101000000000000000000000000 5
16
#80000
b01000001001000000000000000000000 #
b11000001001000000000000000000000 $
0%
1&
06
#90000
b11000000000000000000000000000000 #
b01000010000000000000000000000000 $
1%
0&
b10000000 '
b10000100 (
b100000000000000000000000 )
b100000000000000000000000 *
b00000100 +
b000010000000000000000000 ,
b100000000000000000000000 -
b10000100 .
b0011110000000000000000000 /
b0100000000000000000000000 0
b0000010000000000000000000 1
b10000011 2
b111100000000000000000000 3
b01000001111100000000000000000000 5
#100000
b11000010000000000000000000000000 #
b01000000000000000000000000000000 $
b10000100 '
b10000000 (
b100000000000000000000000 ,
b000010000000000000000000 -
b11000001111100000000000000000000 5
16
17
#110000
b11000000011000000000000000000000 #
b01000000101001100110011001100110 $
b10000000 '
b10000001 (
b111000000000000000000000 )
b101001100110011001100110 *
b00000001 +
b011100000000000000000000 ,
b101001100110011001100110 -
b10000001 .
b0001101100110011001100110 /
b0101001100110011001100110 0
b0011100000000000000000000 1
b01111111 2
b110110011001100110011000 3
b00111111110110011001100110011000 5
06
07
#120000
b01000000110000000000000000000000 #
b11000001010000000110000000000000 $
0%
1&
b10000001 '
b10000010 (
b110000000000000000000000 )
b110000000110000000000000 *
b011000000000000000000000 ,
b110000000110000000000000 -
b10000010 .
b0011000000110000000000000 /
b0110000000110000000000000 0
b0011000000000000000000000 1
b10000001 2
b110000001100000000000000 3
b11000000110000001100000000000000 5
16
17
